BETDisk/BETTranslatorInterface.py
BETDisk/__init__.py
BETDisk/exportBETPolarPlots.py
BETDisk/utils.py
flow360_betdisk-0.1.13.dist-info/METADATA
flow360_betdisk-0.1.13.dist-info/WHEEL
flow360_betdisk-0.1.13.dist-info/RECORD
