Metadata-Version: 2.1
Name: flow360-betdisk
Version: 0.1.13
Summary: 
Author: Flexcompute
Author-email: support@flexcompute.com
Requires-Python: >=3.8,<4.0
Classifier: Programming Language :: Python :: 3
Classifier: Programming Language :: Python :: 3.8
Classifier: Programming Language :: Python :: 3.9
Classifier: Programming Language :: Python :: 3.10
Classifier: Programming Language :: Python :: 3.11
Requires-Dist: scipy (>=1.9.3,<2.0.0)
